data_structures/__init__.py
data_structures/array.py
data_structures/graph.py
data_structures/linked_list.py
data_structures/queue.py
data_structures/stack.py
data_structures/tree.py
laity_data_structures_py-0.0.1.dist-info/LICENSE
laity_data_structures_py-0.0.1.dist-info/METADATA
laity_data_structures_py-0.0.1.dist-info/WHEEL
laity_data_structures_py-0.0.1.dist-info/top_level.txt
laity_data_structures_py-0.0.1.dist-info/RECORD
